django_simple_profiler/__init__.py
django_simple_profiler/functions.py
django_simple_profiler-0.5.1.dist-info/LICENSE
django_simple_profiler-0.5.1.dist-info/METADATA
django_simple_profiler-0.5.1.dist-info/WHEEL
django_simple_profiler-0.5.1.dist-info/top_level.txt
django_simple_profiler-0.5.1.dist-info/RECORD
