Metadata-Version: 2.1
Name: django-simple-profiler
Version: 0.5.1
Summary: Django simple profiler it is a useful tool for Django framework that allows you to profile your views.
Home-page: https://github.com/Sobolev5/django-simple-profiler
Author: Sobolev Andrey
Author-email: email.asobolev@gmail.com
License: UNKNOWN
Platform: UNKNOWN
Classifier: Programming Language :: Python :: 3
Classifier: License :: OSI Approved :: MIT License
Classifier: Operating System :: OS Independent
Requires-Python: >=3.9
License-File: LICENSE
Requires-Dist: terminaltables
Requires-Dist: psutil
